{"sections":{"17574189538c2e5a81":{"type":"apps","settings":{"include_margins":true}},"main":{"type":"main-product","blocks":{"labels":{"type":"labels","settings":{"hide_discount_label":false,"hide_sold_out_label":false,"hide_other_labels":true,"show_label_border":false}},"title":{"type":"title","settings":{"title_size":2,"title_size_mobile":3}},"price":{"type":"price","settings":{"emphasize":false,"price_label_discount":true,"price_label_discount_type":"percentage","price_label_discount_color":"#c00000","price_label_text_discount_color":"#ffffff","show_label_border":false}},"db48bf56-e904-4604-9f21-89d04e9bf249":{"type":"spacer","settings":{"column":"primary","top":"small","bottom":"small","border":true}},"judge_me_reviews_preview_badge_QabBeg":{"type":"shopify:\/\/apps\/judge-me-reviews\/blocks\/preview_badge\/61ccd3b1-a9f2-4160-9fe9-4fec8413e5d8","settings":{}},"variant_picker":{"type":"variant_picker","settings":{"product_variant_style":"swatches-buttons","popup_enable":true,"popup_trigger":"Size\nGröße\nTaille\nTaglia\nTalla","popup_label":"Size guide","popup_content":""}},"quantity_selector":{"type":"quantity_selector","settings":{}},"inventory_notice":{"type":"inventory_notice","settings":{"inventory_limit":27,"align":"left","show_qty":true}},"buy_buttons":{"type":"buy_buttons","settings":{"show_gift_card_recipient":true,"enable_payment_button":true}},"pickup":{"type":"pickup","settings":{}},"trust":{"type":"trust","settings":{"column":"primary","heading":"Shop with confidence","heading_size":2,"show_payment_icons":true,"color_bg":"#f2f2f2","color_text":"#212121","color_icon":"#212121","content_heading_color":false,"show_border":false,"columns_desktop":"2","icon_size":1,"spacing":1,"text_bold":false,"text_1":"Fast shipping","icon_1":"icon-shipment-package","svg-code_1":"","text_2":"Easy exchanges","icon_2":"icon-keyboard-arrow-return","svg-code_2":"","text_3":"Trusted reviews","icon_3":"icon-shield-check","svg-code_3":"","text_4":"Eco materials","icon_4":"icon-ecology-leaf","svg-code_4":"","text_5":"Price guarantee","icon_5":"icon-award-ribbon-star-1","svg-code_5":"","text_6":"","icon_6":"icon-love-it","svg-code_6":""}},"description":{"type":"description","settings":{"column":"secondary","title":"Description","display_collapsible_tab":false,"open":false,"icon":"none","icon_size":2,"color_icon":"rgba(0,0,0,0)","svg-code":""}}},"block_order":["labels","title","price","db48bf56-e904-4604-9f21-89d04e9bf249","judge_me_reviews_preview_badge_QabBeg","variant_picker","quantity_selector","inventory_notice","buy_buttons","pickup","trust","description"],"settings":{"style":"clean","style_clean_mobile":true,"layout-order":"media-left","enable_sticky_content":true,"container":"large","show_breadcrumbs":true,"breadcrumbs_align":"center","enable_zoom":true,"enable_video_looping":false,"product_image_ratio":"1:1","enable_product_image_rounded_corners":false,"enable_gallery_arrows":true,"thumbnails_position":"bottom","thumbnails_ratio":"1:1","thumbnails_show_border":false}},"9904a28f-6381-41fe-96eb-d4a73d60f0a0":{"type":"section-testimonials","blocks":{"template--16580692508926__9904a28f-6381-41fe-96eb-d4a73d60f0a0-1666784019a14d8867-0":{"type":"text","settings":{"media":"quote","svg-code":"","image_round":true,"text":"<p>Use these testimonials to share what customers are saying about your products and your brand.<\/p>","name":"Customer name","source":"Source"}},"template--16580692508926__9904a28f-6381-41fe-96eb-d4a73d60f0a0-1666784019a14d8867-1":{"type":"text","settings":{"media":"instagram","svg-code":"","image_round":true,"text":"<p>Use these testimonials to share what customers are saying about your products and your brand.<\/p>","name":"Customer name","source":"Source"}},"template--16580692508926__9904a28f-6381-41fe-96eb-d4a73d60f0a0-1666784019a14d8867-2":{"type":"text","settings":{"media":"x","svg-code":"","image_round":true,"text":"<p>Use these testimonials to share what customers are saying about your products and your brand.<\/p>","name":"Customer name","source":"Source"}}},"block_order":["template--16580692508926__9904a28f-6381-41fe-96eb-d4a73d60f0a0-1666784019a14d8867-0","template--16580692508926__9904a28f-6381-41fe-96eb-d4a73d60f0a0-1666784019a14d8867-1","template--16580692508926__9904a28f-6381-41fe-96eb-d4a73d60f0a0-1666784019a14d8867-2"],"disabled":true,"settings":{"title":"Testimonials","desc":"","heading_alignment":"center","autoplay":true,"autoplay_speed":8,"style_desktop":"grid","desktop_carousel":false,"mobile_carousel":true,"section_link_title":"View all","section_link_link":"","section_link_style":"link link--arrow","padding_top":0,"padding_bottom":0}},"product-recommendations":{"type":"section-product-recommendations","settings":{"title":"You may also like","desc":"","heading_alignment":"center","section_width":"large","maximum_products":10,"grid":3,"grid_mobile":"1","divider_top":false,"divider_bottom":false,"section_link_title":"View all","section_link_link":"shopify:\/\/collections\/fine-art-print-collection","section_link_style":"link link--arrow","padding_top":0,"padding_bottom":0,"section_bottom_margin":false}},"section_image_grid_JrPWQN":{"type":"section-image-grid","blocks":{"image_eYzTad":{"type":"image","disabled":true,"settings":{"text_border_color":false,"title":"Image block","text":"Use these image blocks to tell your story, promote your products or create a beautiful gallery.","link":"","text_alignment":"bottom"}},"text_RnV7rj":{"type":"text","disabled":true,"settings":{"title":"Text block","text":"<p>Use these text blocks to promote seasonal sales, store events or to tell your brand's story.<\/p>","link_text":"Learn more","link":"","bg_color":"#f2f2f2","text_color":"#212121","text_heading_color":false,"text_border_color":false}},"image_cUpRb7":{"type":"image","disabled":true,"settings":{"text_border_color":false,"title":"Image block","text":"Use these image blocks to tell your story, promote your products or create a beautiful gallery.","link":"","text_alignment":"bottom"}},"text_TRji84":{"type":"text","disabled":true,"settings":{"title":"Text block","text":"<p>Use these text blocks to promote seasonal sales, store events or to tell your brand's story.<\/p>","link_text":"Learn more","link":"","bg_color":"#f2f2f2","text_color":"#212121","text_heading_color":false,"text_border_color":false}}},"block_order":["image_eYzTad","text_RnV7rj","image_cUpRb7","text_TRji84"],"disabled":true,"name":"Image grid with text","settings":{"featured":true,"section_height":450,"section_height_mobile":350,"width":"full","overlay_color":"#000000","overlay_strength":10,"button_style":"c-btn c-btn--hollow","padding_top":0,"padding_bottom":0,"section_bottom_margin":false}}},"order":["17574189538c2e5a81","main","9904a28f-6381-41fe-96eb-d4a73d60f0a0","product-recommendations","section_image_grid_JrPWQN"]}